README.txt
setup.py
ATC/App.py
ATC/Command.py
ATC/Device.py
ATC/Element.py
ATC/Memory.py
ATC/ScreenRecord.py
ATC/SurfaceStatsCollector.py
ATC/System.py
ATC/__init__.py
ATC.egg-info/PKG-INFO
ATC.egg-info/SOURCES.txt
ATC.egg-info/dependency_links.txt
ATC.egg-info/top_level.txt
ATC.egg-info/zip-safe