Metadata-Version: 1.1
Name: ATC
Version: 1.0.1
Summary: 安卓手机自动化测试驱动包.
Home-page: https://my.oschina.net/hibony/blog
Author: bony
Author-email: boyne@foxmail.com
License: MIT
Keywords: test python package
Platform: UNKNOWN
Classifier: License :: OSI Approved :: MIT License
Classifier: Programming Language :: Python
Classifier: Intended Audience :: Developers
Classifier: Operating System :: OS Independent
